{
  "accreditationAddressLabel": "Accreditation address",
  "accreditationDetailsHeading": "Accreditation details",
  "accreditationNumberLabel": "Accreditation number",
  "authorisedByLabel": "Authorised by",
  "cancelButton": "Cancel",
  "decemberWasteLabel": "December waste",
  "decemberWasteNo": "No",
  "decemberWasteYes": "Yes",
  "errorSummaryTitle": "There is a problem",
  "helpSummary": "Can't find the producer or compliance scheme?",
  "issueCommentsLabel": "Issue comments",
  "issuedByLabel": "Issued by",
  "issuedDateLabel": "Issued date",
  "issuedToLabel": "Packaging waste producer or compliance scheme",
  "materialLabel": "Material",
  "notProvided": "Not provided",
  "notesLabel": "Add issuer notes (optional)",
  "pernDetailsHeading": "PERN details",
  "perns": {
    "caption": "Create PERN",
    "checkHeading": "Check before creating PERN",
    "checkIntroText": "Check the following information is correct before creating this PERN.",
    "checkAuthorisationText": "When created, the PERN will need to be authorised and issued by a PERN signatory from your company.",
    "checkInsetText": "Any information that is not shown here will be automatically populated when the PERN is issued.",
    "checkPageTitle": "Check before creating PERN",
    "createButton": "Create PERN",
    "cancelButton": "Cancel without saving",
    "helpText": "PERNs can only be issued to packaging waste producers and compliance schemes who have registered with regulators. If the buyer you're looking for is not appearing, check that you have spelled the name correctly and that they are registered with a regulator.",
    "notesHint": "These notes will appear on the PERN",
    "pageTitle": "Create a PERN",
    "recipientLabel": "Enter who this PERN will be issued to",
    "submitButton": "Continue",
    "successHeading": "PERN created",
    "successNextStepsText": "Your PERN has been created as a draft. You can view and manage it from your registration dashboard.",
    "successPageTitle": "PERN created",
    "successTonnageLabel": "Tonnage",
    "tonnageLabel": "Enter PERN tonnage"
  },
  "positionLabel": "Position",
  "prnDetailsHeading": "PRN details",
  "prns": {
    "caption": "Create PRN",
    "checkHeading": "Check before creating PRN",
    "checkIntroText": "Check the following information is correct before creating this PRN.",
    "checkAuthorisationText": "When created, the PRN will need to be authorised and issued by a PRN signatory from your company.",
    "checkInsetText": "Any information that is not shown here will be automatically populated when the PRN is issued.",
    "checkPageTitle": "Check before creating PRN",
    "createButton": "Create PRN",
    "cancelButton": "Cancel without saving",
    "helpText": "PRNs can only be issued to packaging waste producers and compliance schemes who have registered with regulators. If the buyer you're looking for is not appearing, check that you have spelled the name correctly and that they are registered with a regulator.",
    "notesHint": "These notes will appear on the PRN",
    "pageTitle": "Create a PRN",
    "recipientLabel": "Enter who this PRN will be issued to",
    "submitButton": "Continue",
    "successHeading": "PRN created",
    "successNextStepsText": "Your PRN has been created as a draft. You can view and manage it from your registration dashboard.",
    "successPageTitle": "PRN created",
    "successTonnageLabel": "Tonnage",
    "tonnageLabel": "Enter PRN tonnage"
  },
  "processToBeUsedLabel": "Process to be used",
  "recipientHint": "Start typing the name of the packaging waste producer or compliance scheme",
  "recipientSummaryLabel": "Issued to",
  "selectOption": "Select an option",
  "successNextStepsHeading": "What happens next",
  "successReturnLink": "Return to registration dashboard",
  "tonnageHint": "Enter a whole number without decimal places",
  "tonnageInWordsLabel": "Tonnage in words",
  "tonnageLabel": "Tonnage",
  "tonnageSuffix": "tonnes"
}
